godot_api_refs/__init__.py
godot_api_refs/__main__.py
godot_api_refs-0.1.3.dist-info/LICENSE
godot_api_refs-0.1.3.dist-info/METADATA
godot_api_refs-0.1.3.dist-info/WHEEL
godot_api_refs-0.1.3.dist-info/top_level.txt
godot_api_refs-0.1.3.dist-info/RECORD
