Metadata-Version: 2.1
Name: godot-api-refs
Version: 0.1.3
Summary: Create links for Godot class names to Godot api help files
Home-page: https://github.com/DouglasWebster/godot-api-refs
Author: Douglas Webster
Author-email: douglas.webster2107@gmail.com
License: UNKNOWN
Project-URL: Bug Tracker, https://github.com/DouglasWebster/godot-api-refs/issues
Keywords: godot,gdscript,documentation,restructured,sphinx
Platform: UNKNOWN
Classifier: Programming Language :: Python :: 3
Classifier: License :: OSI Approved :: MIT License
Classifier: Operating System :: OS Independent
Classifier: Development Status :: 4 - Beta
Requires-Python: >=3.6
Requires-Dist: ghapi
